{
  "academic": {
    "canonical_title": "No Free Lunch Theorems for Optimization",
    "components": [
      {
        "confidence": "high",
        "contribution": 0.031375,
        "metric": "citation_count",
        "normalized": 0.062749,
        "provenance_url": "https://openalex.org/W2151554678",
        "retrieved_at": "2026-06-29",
        "source": "OpenAlex",
        "status": "present",
        "value": 13940.0,
        "weight": 0.5
      },
      {
        "metric": "library_holdings",
        "missing_data_penalty": 0.1,
        "note": "recorded as missing; penalized by rule, never imputed",
        "status": "missing",
        "weight": 0.2
      },
      {
        "metric": "sustained_readership",
        "missing_data_penalty": 0.025,
        "note": "recorded as missing; penalized by rule, never imputed",
        "status": "missing",
        "weight": 0.05
      },
      {
        "metric": "syllabus_adoptions",
        "missing_data_penalty": 0.125,
        "note": "recorded as missing; penalized by rule, never imputed",
        "status": "missing",
        "weight": 0.25
      }
    ],
    "conflict_flag": false,
    "rank": 24,
    "scenario": "academic",
    "score": -0.218625,
    "work_id": "paper-0040",
    "work_type": "paper"
  },
  "broad_influence": {
    "canonical_title": "No Free Lunch Theorems for Optimization",
    "components": [
      {
        "confidence": "high",
        "contribution": 0.01255,
        "metric": "citation_count",
        "normalized": 0.062749,
        "provenance_url": "https://openalex.org/W2151554678",
        "retrieved_at": "2026-06-29",
        "source": "OpenAlex",
        "status": "present",
        "value": 13940.0,
        "weight": 0.2
      },
      {
        "metric": "library_holdings",
        "missing_data_penalty": 0.125,
        "note": "recorded as missing; penalized by rule, never imputed",
        "status": "missing",
        "weight": 0.25
      },
      {
        "metric": "sustained_readership",
        "missing_data_penalty": 0.2,
        "note": "recorded as missing; penalized by rule, never imputed",
        "status": "missing",
        "weight": 0.4
      },
      {
        "metric": "syllabus_adoptions",
        "missing_data_penalty": 0.075,
        "note": "recorded as missing; penalized by rule, never imputed",
        "status": "missing",
        "weight": 0.15
      }
    ],
    "conflict_flag": false,
    "rank": 24,
    "scenario": "broad_influence",
    "score": -0.38745,
    "work_id": "paper-0040",
    "work_type": "paper"
  },
  "governance_practitioner": {
    "canonical_title": "No Free Lunch Theorems for Optimization",
    "components": [
      {
        "confidence": "high",
        "contribution": 0.015687,
        "metric": "citation_count",
        "normalized": 0.062749,
        "provenance_url": "https://openalex.org/W2151554678",
        "retrieved_at": "2026-06-29",
        "source": "OpenAlex",
        "status": "present",
        "value": 13940.0,
        "weight": 0.25
      },
      {
        "metric": "library_holdings",
        "missing_data_penalty": 0.15,
        "note": "recorded as missing; penalized by rule, never imputed",
        "status": "missing",
        "weight": 0.3
      },
      {
        "metric": "sustained_readership",
        "missing_data_penalty": 0.05,
        "note": "recorded as missing; penalized by rule, never imputed",
        "status": "missing",
        "weight": 0.1
      },
      {
        "metric": "syllabus_adoptions",
        "missing_data_penalty": 0.175,
        "note": "recorded as missing; penalized by rule, never imputed",
        "status": "missing",
        "weight": 0.35
      }
    ],
    "conflict_flag": false,
    "rank": 24,
    "scenario": "governance_practitioner",
    "score": -0.359313,
    "work_id": "paper-0040",
    "work_type": "paper"
  }
}
